stateflow/__init__.py
stateflow/call_result.py
stateflow/common.py
stateflow/decorators.py
stateflow/errors.py
stateflow/forwarders.py
stateflow/notifier.py
stateflow/utils.py
stateflow/var.py
stateflow/var_old.py
stateflow/wrapping.py
stateflow/examples/__init__.py
stateflow/examples/basic.py
stateflow/test/__init__.py
stateflow/test/test_forwarders.py
stateflow/test/test_reactive.py
stateflow/wrappers/__init__.py
stateflow/wrappers/axes.py
stateflow/wrappers/collections.py
stateflow-0.0.2.dist-info/METADATA
stateflow-0.0.2.dist-info/RECORD
stateflow-0.0.2.dist-info/WHEEL
stateflow-0.0.2.dist-info/top_level.txt
